<?xml version="1.0" encoding="UTF-8"?><record_update table="sys_di_task_def_solution_def">
    <sys_di_task_def_solution_def action="DELETE">
        <document_config display_value="Default">ba8dcf15435152104b6520d9bab8f281</document_config>
        <ml_capability_definition_base display_value="docintel_pdf_preprocessing_workflow_3ab1ef6a2bc27a906bcdf559f291bf45">d1d1e3aa2bc27a906bcdf559f291bf1a</ml_capability_definition_base>
        <solution_type display_value="PDF">2941fd6cb70a2110cbc68b91ee11a972</solution_type>
        <sys_class_name>sys_di_task_def_solution_def</sys_class_name>
        <sys_created_by>admin</sys_created_by>
        <sys_created_on>2025-12-29 13:58:13</sys_created_on>
        <sys_id>15d1e3aa2bc27a906bcdf559f291bf1e</sys_id>
        <sys_mod_count>0</sys_mod_count>
        <sys_name/>
        <sys_package display_value="Lab AI Knowledge Companion" source="x_snc_lab_ai_kno_0">26a4fa2a2b423a906bcdf559f291bf5d</sys_package>
        <sys_policy/>
        <sys_scope display_value="Lab AI Knowledge Companion">26a4fa2a2b423a906bcdf559f291bf5d</sys_scope>
        <sys_update_name>sys_di_task_def_solution_def_15d1e3aa2bc27a906bcdf559f291bf1e</sys_update_name>
        <sys_updated_by>admin</sys_updated_by>
        <sys_updated_on>2025-12-29 13:58:13</sys_updated_on>
        <task_definition display_value="Read W-9 form">3ab1ef6a2bc27a906bcdf559f291bf45</task_definition>
    </sys_di_task_def_solution_def>
    <sys_update_version action="INSERT_OR_UPDATE">
        <action>DELETE</action>
        <application display_value="Lab AI Knowledge Companion">26a4fa2a2b423a906bcdf559f291bf5d</application>
        <file_path/>
        <instance_id>d655b87edb400214f697684e13961904</instance_id>
        <instance_name>crwfhackathon4</instance_name>
        <name>sys_di_task_def_solution_def_15d1e3aa2bc27a906bcdf559f291bf1e</name>
        <payload><![CDATA[<?xml version="1.0" encoding="UTF-8"?><record_update table="sys_di_task_def_solution_def"><sys_di_task_def_solution_def action="INSERT_OR_UPDATE"><document_config display_value="Default">ba8dcf15435152104b6520d9bab8f281</document_config><ml_capability_definition_base display_value="docintel_pdf_preprocessing_workflow_3ab1ef6a2bc27a906bcdf559f291bf45">d1d1e3aa2bc27a906bcdf559f291bf1a</ml_capability_definition_base><solution_type display_value="PDF">2941fd6cb70a2110cbc68b91ee11a972</solution_type><sys_class_name>sys_di_task_def_solution_def</sys_class_name><sys_created_by>admin</sys_created_by><sys_created_on>2025-12-29 13:58:13</sys_created_on><sys_id>15d1e3aa2bc27a906bcdf559f291bf1e</sys_id><sys_mod_count>0</sys_mod_count><sys_name/><sys_package display_value="Lab AI Knowledge Companion" source="x_snc_lab_ai_kno_0">26a4fa2a2b423a906bcdf559f291bf5d</sys_package><sys_policy/><sys_scope display_value="Lab AI Knowledge Companion">26a4fa2a2b423a906bcdf559f291bf5d</sys_scope><sys_update_name>sys_di_task_def_solution_def_15d1e3aa2bc27a906bcdf559f291bf1e</sys_update_name><sys_updated_by>admin</sys_updated_by><sys_updated_on>2025-12-29 13:58:13</sys_updated_on><task_definition display_value="Read W-9 form">3ab1ef6a2bc27a906bcdf559f291bf45</task_definition></sys_di_task_def_solution_def></record_update>]]></payload>
        <payload_hash>1782418476</payload_hash>
        <record_name/>
        <reverted_from/>
        <source>27957aa63bc272901249feb643e45a4c</source>
        <source_table>sys_update_set</source_table>
        <state>previous</state>
        <sys_created_by>admin</sys_created_by>
        <sys_created_on>2025-12-29 13:58:13</sys_created_on>
        <sys_id>95d1e3aa2bc27a906bcdf559f291bf21</sys_id>
        <sys_mod_count>0</sys_mod_count>
        <sys_recorded_at>19b6a66fd270000001</sys_recorded_at>
        <sys_updated_by>admin</sys_updated_by>
        <sys_updated_on>2025-12-29 13:58:13</sys_updated_on>
        <type>Task Solution Definition</type>
        <update_guid>15d1e3aa9ec27a90fe0190dbab89e820</update_guid>
        <update_guid_history>15d1e3aa9ec27a90fe0190dbab89e820:1782418476</update_guid_history>
    </sys_update_version>
    <sys_metadata_delete action="INSERT_OR_UPDATE">
        <sys_audit_delete/>
        <sys_class_name>sys_metadata_delete</sys_class_name>
        <sys_created_by>admin</sys_created_by>
        <sys_created_on>2026-01-05 20:18:34</sys_created_on>
        <sys_db_object display_value="" name="sys_di_task_def_solution_def">sys_di_task_def_solution_def</sys_db_object>
        <sys_id>18368e82d4ac49088691077c1e220684</sys_id>
        <sys_metadata>15d1e3aa2bc27a906bcdf559f291bf1e</sys_metadata>
        <sys_mod_count>0</sys_mod_count>
        <sys_name/>
        <sys_package display_value="Lab AI Knowledge Companion" source="x_snc_lab_ai_kno_0">26a4fa2a2b423a906bcdf559f291bf5d</sys_package>
        <sys_parent/>
        <sys_policy/>
        <sys_scope display_value="Lab AI Knowledge Companion">26a4fa2a2b423a906bcdf559f291bf5d</sys_scope>
        <sys_scope_delete display_value="">130e489d6c344ec08e433139d11dc400</sys_scope_delete>
        <sys_update_name>sys_di_task_def_solution_def_15d1e3aa2bc27a906bcdf559f291bf1e</sys_update_name>
        <sys_update_version display_value="sys_di_task_def_solution_def_15d1e3aa2bc27a906bcdf559f291bf1e">95d1e3aa2bc27a906bcdf559f291bf21</sys_update_version>
        <sys_updated_by>admin</sys_updated_by>
        <sys_updated_on>2026-01-05 20:18:34</sys_updated_on>
    </sys_metadata_delete>
</record_update>
